slate/__about__.py
slate/__init__.py
slate/__main__.py
slate/color.py
slate/color_info.py
slate/core.py
slate/event.py
slate/key_names.py
slate/py.typed
slate/screen.py
slate/span.py
slate/terminal.py
tests/__init__.py
tests/test_color.py
tests/test_core.py
tests/test_event.py
tests/test_screen.py
tests/test_span.py
tests/test_terminal.py
sh40_slate-0.10.1.dist-info/METADATA
sh40_slate-0.10.1.dist-info/WHEEL
sh40_slate-0.10.1.dist-info/entry_points.txt
sh40_slate-0.10.1.dist-info/licenses/LICENSE
sh40_slate-0.10.1.dist-info/RECORD
