Metadata-Version: 2.4
Name: sh40-slate
Version: 0.10.1
Summary: A powerful terminal management library.
Project-URL: Documentation, https://github.com/shade40/slate#readme
Project-URL: Issues, https://github.com/shade40/slate/issues
Project-URL: Source, https://github.com/shade40/slate
Author-email: bczsalba <bczsalba@gmail.com>
License-Expression: MIT
License-File: LICENSE
Classifier: Development Status :: 4 - Beta
Classifier: Environment :: Console
Classifier: Intended Audience :: Developers
Classifier: License :: OSI Approved :: MIT License
Classifier: Operating System :: MacOS
Classifier: Operating System :: POSIX :: Linux
Classifier: Programming Language :: Python :: 3.8
Classifier: Programming Language :: Python :: 3.9
Classifier: Programming Language :: Python :: 3.10
Classifier: Programming Language :: Python :: 3.11
Classifier: Programming Language :: Python :: Implementation :: CPython
Classifier: Programming Language :: Python :: Implementation :: PyPy
Classifier: Topic :: Software Development :: Libraries
Classifier: Topic :: Terminals
Classifier: Typing :: Typed
Requires-Python: >=3.8
